.gitignore
.travis.yml
AUTHORS.rst
CHANGES.rst
CONTRIBUTING.rst
LICENSE.txt
MANIFEST.in
README.md
README.rst
setup.py
tox.ini
bootstrap_span/__init__.py
bootstrap_span/form_span.py
bootstrap_span/templatetags/__init__.py
bootstrap_span/templatetags/bootstrap_span.py
django_bootstrap_span.egg-info/PKG-INFO
django_bootstrap_span.egg-info/SOURCES.txt
django_bootstrap_span.egg-info/dependency_links.txt
django_bootstrap_span.egg-info/requires.txt
django_bootstrap_span.egg-info/top_level.txt
docs/Makefile
docs/conf.py
docs/index.rst
docs/make.bat
tests/test_single_field.py
tests/myunittestsite/__init__.py
tests/myunittestsite/forms.py
tests/myunittestsite/models.py
tests/myunittestsite/settings.py
tests/myunittestsite/urls.py
tests/myunittestsite/views.py
tests/myunittestsite/templates/myunittestsite/form_template.html