Metadata-Version: 1.0
Name: django-bootstrap-span
Version: 0.0.3
Summary: Django bootstrap span adds class=spanN support in forms input elements
Home-page: https://github.com/stumc/django-bootstrap-span
Author: Stuart McMillan
Author-email: smcmillan@usefulautomation.com
License: UNKNOWN
Download-URL: https://github.com/stumc/django-bootstrap-span/tarball/0.0.3
Keywords: django,bootstrap,class,span,form,input,width
Platform: UNKNOWN
Classifier: Development Status :: 4 - Beta
Classifier: Operating System :: OS Independent
Classifier: Intended Audience :: Developers
Classifier: License :: OSI Approved :: BSD License
Classifier: Programming Language :: Python
Classifier: Programming Language :: Python :: 2
Classifier: Programming Language :: Python :: 2.7
Classifier: Programming Language :: Python :: 3
Classifier: Programming Language :: Python :: 3.3
Classifier: Programming Language :: Python :: 3.4
Classifier: Topic :: Software Development :: Libraries
Classifier: Topic :: Utilities
Classifier: Environment :: Web Environment
Classifier: Framework :: Django
